tensorhive/__init__.py
tensorhive/__main__.py
tensorhive/authorization.py
tensorhive/cli.py
tensorhive/config.py
tensorhive/database.py
tensorhive/hosts_config.ini
tensorhive/mailbot_config.ini
tensorhive/main_config.ini
tensorhive/api/APIServer.py
tensorhive/api/__init__.py
tensorhive/api/api_specification.yml
tensorhive/app/__init__.py
tensorhive/app/web/AppServer.py
tensorhive/app/web/__init__.py
tensorhive/app/web/dist/index.html
tensorhive/app/web/dist/static/config.json
tensorhive/app/web/dist/static/AdminLTE/AdminLTE.min.css
tensorhive/app/web/dist/static/AdminLTE/app.min.js
tensorhive/app/web/dist/static/AdminLTE/skin-blue.min.css
tensorhive/app/web/dist/static/bootstrap/bootstrap.min.css
tensorhive/app/web/dist/static/bootstrap/bootstrap.min.css.map.css
tensorhive/app/web/dist/static/bootstrap/bootstrap.min.js
tensorhive/app/web/dist/static/css/app.ee0e09f7bb468cdd57cdcc0573874ef5.css
tensorhive/app/web/dist/static/favicon/android-icon-144x144.png
tensorhive/app/web/dist/static/favicon/android-icon-192x192.png
tensorhive/app/web/dist/static/favicon/android-icon-36x36.png
tensorhive/app/web/dist/static/favicon/android-icon-48x48.png
tensorhive/app/web/dist/static/favicon/android-icon-72x72.png
tensorhive/app/web/dist/static/favicon/android-icon-96x96.png
tensorhive/app/web/dist/static/favicon/apple-icon-114x114.png
tensorhive/app/web/dist/static/favicon/apple-icon-120x120.png
tensorhive/app/web/dist/static/favicon/apple-icon-144x144.png
tensorhive/app/web/dist/static/favicon/apple-icon-152x152.png
tensorhive/app/web/dist/static/favicon/apple-icon-180x180.png
tensorhive/app/web/dist/static/favicon/apple-icon-57x57.png
tensorhive/app/web/dist/static/favicon/apple-icon-60x60.png
tensorhive/app/web/dist/static/favicon/apple-icon-72x72.png
tensorhive/app/web/dist/static/favicon/apple-icon-76x76.png
tensorhive/app/web/dist/static/favicon/apple-icon-precomposed.png
tensorhive/app/web/dist/static/favicon/apple-icon.png
tensorhive-0.2.4.dist-info/LICENSE
tensorhive-0.2.4.dist-info/METADATA
tensorhive-0.2.4.dist-info/WHEEL
tensorhive-0.2.4.dist-info/entry_points.txt
tensorhive-0.2.4.dist-info/top_level.txt
tensorhive-0.2.4.dist-info/RECORD
